wrapper/__init__.py
wrapper/wrapper.py
py_exec_wrapper-1.0.1.dist-info/LICENSE
py_exec_wrapper-1.0.1.dist-info/METADATA
py_exec_wrapper-1.0.1.dist-info/WHEEL
py_exec_wrapper-1.0.1.dist-info/top_level.txt
py_exec_wrapper-1.0.1.dist-info/RECORD
