Metadata-Version: 2.1
Name: py-exec-wrapper
Version: 1.0.1
Summary: Binary file wrapper
Author-email: myback <54638513+myback@users.noreply.github.com>
License: MIT License
Project-URL: Homepage, https://github.com/myback/py-exec-wrapper
Project-URL: Bug Tracker, https://github.com/myback/py-exec-wrapper/issues
Classifier: Programming Language :: Python :: 3.10
Classifier: Programming Language :: Python :: 3.11
Classifier: License :: OSI Approved :: MIT License
Requires-Python: >=3.10
License-File: LICENSE
